CHANGES.txt
LICENSE.txt
README.txt
bootstrap.py
buildout.cfg
setup.py
src/z3c/__init__.py
src/z3c.layer.minimal.egg-info/PKG-INFO
src/z3c.layer.minimal.egg-info/SOURCES.txt
src/z3c.layer.minimal.egg-info/dependency_links.txt
src/z3c.layer.minimal.egg-info/namespace_packages.txt
src/z3c.layer.minimal.egg-info/not-zip-safe
src/z3c.layer.minimal.egg-info/requires.txt
src/z3c.layer.minimal.egg-info/top_level.txt
src/z3c/layer/__init__.py
src/z3c/layer/minimal/README.txt
src/z3c/layer/minimal/__init__.py
src/z3c/layer/minimal/configure.zcml
src/z3c/layer/minimal/zope.app.form.browser.zcml
src/z3c/layer/minimal/zope.app.http.exception.zcml
src/z3c/layer/minimal/zope.app.publication.zcml
src/z3c/layer/minimal/zope.app.publisher.browser.zcml
src/z3c/layer/minimal/zope.traversing.browser.zcml
src/z3c/layer/minimal/zope.traversing.zcml
src/z3c/layer/minimal/browser/__init__.py
src/z3c/layer/minimal/browser/configure.zcml
src/z3c/layer/minimal/browser/notfound.pt
src/z3c/layer/minimal/browser/systemerror.pt
src/z3c/layer/minimal/browser/unauthorized.pt
src/z3c/layer/minimal/browser/user.pt
src/z3c/layer/minimal/locales/z3c.layer.minimal.pot
src/z3c/layer/minimal/locales/de/LC_MESSAGES/z3c.layer.minimal.mo
src/z3c/layer/minimal/locales/de/LC_MESSAGES/z3c.layer.minimal.po
src/z3c/layer/minimal/locales/hu/LC_MESSAGES/z3c.layer.minimal.mo
src/z3c/layer/minimal/locales/hu/LC_MESSAGES/z3c.layer.minimal.po
src/z3c/layer/minimal/locales/ro/LC_MESSAGES/z3c.layer.minimal.mo
src/z3c/layer/minimal/locales/ro/LC_MESSAGES/z3c.layer.minimal.po
src/z3c/layer/minimal/tests/__init__.py
src/z3c/layer/minimal/tests/bugfixes.txt
src/z3c/layer/minimal/tests/configure.zcml
src/z3c/layer/minimal/tests/error_macros.pt
src/z3c/layer/minimal/tests/ftesting.zcml
src/z3c/layer/minimal/tests/page.pt
src/z3c/layer/minimal/tests/page_macros.pt
src/z3c/layer/minimal/tests/test_layer.py
src/z3c/layer/minimal/tests/view_macros.pt